htmlatex/__init__.py
htmlatex/__main__.py
htmlatex-0.1.0.dist-info/WHEEL
htmlatex-0.1.0.dist-info/METADATA
htmlatex-0.1.0.dist-info/RECORD
