Metadata-Version: 2.1
Name: htmlatex
Version: 0.1.0
Summary: 
Author: Linus
Author-email: linuskmr.dev@gmail.com
Requires-Python: >=3.8,<4.0
Classifier: Programming Language :: Python :: 3
Classifier: Programming Language :: Python :: 3.10
Classifier: Programming Language :: Python :: 3.8
Classifier: Programming Language :: Python :: 3.9
Requires-Dist: beautifulsoup4 (>=4.11.1,<5.0.0)
